Metadata-Version: 2.1
Name: web3-metis
Version: 5.24.1.4
Summary: Web3.py
Home-page: https://github.com/thimper/web3.py
Author: Max Lau
Author-email: pipermerriam@gmail.com
License: MIT
Keywords: ethereum
Platform: UNKNOWN
Classifier: Development Status :: 5 - Production/Stable
Classifier: Intended Audience :: Developers
Classifier: License :: OSI Approved :: MIT License
Classifier: Natural Language :: English
Classifier: Programming Language :: Python :: 3
Classifier: Programming Language :: Python :: 3.6
Classifier: Programming Language :: Python :: 3.7
Classifier: Programming Language :: Python :: 3.8
Classifier: Programming Language :: Python :: 3.9
Requires-Python: >=3.6,<4
Requires-Dist: aiohttp (<4,>=3.7.4.post0)
Requires-Dist: eth-abi (<3.0.0,>=2.0.0b6)
Requires-Dist: eth-account (<0.6.0,>=0.5.6)
Requires-Dist: eth-hash[pycryptodome] (<1.0.0,>=0.2.0)
Requires-Dist: eth-typing (<3.0.0,>=2.0.0)
Requires-Dist: eth-utils (<2.0.0,>=1.9.5)
Requires-Dist: hexbytes (<1.0.0,>=0.1.0)
Requires-Dist: ipfshttpclient (==0.8.0a2)
Requires-Dist: jsonschema (<4.0.0,>=3.2.0)
Requires-Dist: lru-dict (<2.0.0,>=1.1.6)
Requires-Dist: protobuf (<4,>=3.10.0)
Requires-Dist: requests (<3.0.0,>=2.16.0)
Requires-Dist: websockets (<10,>=9.1)
Requires-Dist: pywin32 (>=223) ; platform_system == "Windows"
Requires-Dist: typing-extensions (<4,>=3.7.4.1) ; python_version < "3.8"
Provides-Extra: dev
Requires-Dist: eth-tester[py-evm] (==v0.5.0-beta.4) ; extra == 'dev'
Requires-Dist: py-geth (<4,>=3.5.0) ; extra == 'dev'
Requires-Dist: flake8 (==3.8.3) ; extra == 'dev'
Requires-Dist: isort (<4.3.5,>=4.2.15) ; extra == 'dev'
Requires-Dist: mypy (==0.812) ; extra == 'dev'
Requires-Dist: mock ; extra == 'dev'
Requires-Dist: sphinx-better-theme (>=0.1.4) ; extra == 'dev'
Requires-Dist: click (>=5.1) ; extra == 'dev'
Requires-Dist: configparser (==3.5.0) ; extra == 'dev'
Requires-Dist: contextlib2 (>=0.5.4) ; extra == 'dev'
Requires-Dist: py-solc (>=0.4.0) ; extra == 'dev'
Requires-Dist: pytest (<5.0.0,>=4.4.0) ; extra == 'dev'
Requires-Dist: sphinx (<4,>=3.0) ; extra == 'dev'
Requires-Dist: sphinx-rtd-theme (>=0.1.9) ; extra == 'dev'
Requires-Dist: toposort (>=1.4) ; extra == 'dev'
Requires-Dist: towncrier (==18.5.0) ; extra == 'dev'
Requires-Dist: urllib3 ; extra == 'dev'
Requires-Dist: wheel ; extra == 'dev'
Requires-Dist: bumpversion ; extra == 'dev'
Requires-Dist: flaky (<4,>=3.7.0) ; extra == 'dev'
Requires-Dist: hypothesis (<6,>=3.31.2) ; extra == 'dev'
Requires-Dist: pytest-asyncio (<0.11,>=0.10.0) ; extra == 'dev'
Requires-Dist: pytest-mock (<2,>=1.10) ; extra == 'dev'
Requires-Dist: pytest-pythonpath (>=0.3) ; extra == 'dev'
Requires-Dist: pytest-watch (<5,>=4.2) ; extra == 'dev'
Requires-Dist: pytest-xdist (<2,>=1.29) ; extra == 'dev'
Requires-Dist: setuptools (>=38.6.0) ; extra == 'dev'
Requires-Dist: tox (>=1.8.0) ; extra == 'dev'
Requires-Dist: tqdm (<5,>4.32) ; extra == 'dev'
Requires-Dist: twine (<2,>=1.13) ; extra == 'dev'
Requires-Dist: pluggy (==0.13.1) ; extra == 'dev'
Requires-Dist: when-changed (<0.4,>=0.3.0) ; extra == 'dev'
Provides-Extra: docs
Requires-Dist: mock ; extra == 'docs'
Requires-Dist: sphinx-better-theme (>=0.1.4) ; extra == 'docs'
Requires-Dist: click (>=5.1) ; extra == 'docs'
Requires-Dist: configparser (==3.5.0) ; extra == 'docs'
Requires-Dist: contextlib2 (>=0.5.4) ; extra == 'docs'
Requires-Dist: py-geth (<4,>=3.5.0) ; extra == 'docs'
Requires-Dist: py-solc (>=0.4.0) ; extra == 'docs'
Requires-Dist: pytest (<5.0.0,>=4.4.0) ; extra == 'docs'
Requires-Dist: sphinx (<4,>=3.0) ; extra == 'docs'
Requires-Dist: sphinx-rtd-theme (>=0.1.9) ; extra == 'docs'
Requires-Dist: toposort (>=1.4) ; extra == 'docs'
Requires-Dist: towncrier (==18.5.0) ; extra == 'docs'
Requires-Dist: urllib3 ; extra == 'docs'
Requires-Dist: wheel ; extra == 'docs'
Provides-Extra: linter
Requires-Dist: flake8 (==3.8.3) ; extra == 'linter'
Requires-Dist: isort (<4.3.5,>=4.2.15) ; extra == 'linter'
Requires-Dist: mypy (==0.812) ; extra == 'linter'
Provides-Extra: tester
Requires-Dist: eth-tester[py-evm] (==v0.5.0-beta.4) ; extra == 'tester'
Requires-Dist: py-geth (<4,>=3.5.0) ; extra == 'tester'
